distributions_chitts/GaussianDistribution.py
distributions_chitts/GeneralDistribution.py
distributions_chitts/__init__.py
distributions_chitts-0.1.dist-info/METADATA
distributions_chitts-0.1.dist-info/WHEEL
distributions_chitts-0.1.dist-info/top_level.txt
distributions_chitts-0.1.dist-info/RECORD
